{"name":"学习记录","slug":"学习记录","count":2,"postlist":[{"title":"读雷梓峰师兄毕业论文后感","uid":"cc84581c6a8126f374123128fd19c3f0","slug":"读雷梓峰师兄毕业论文后感","date":"2023-02-21T08:06:28.000Z","updated":"2023-02-21T08:17:54.920Z","comments":true,"path":"api/articles/读雷梓峰师兄毕业论文后感.json","keywords":null,"cover":null,"text":"","link":"","photos":[],"count_time":{"symbolsCount":0,"symbolsTime":"1 mins."},"categories":[{"name":"学习记录","slug":"学习记录","count":2,"path":"api/categories/学习记录.json"}],"tags":[{"name":"博弈论","slug":"博弈论","count":1,"path":"api/tags/博弈论.json"},{"name":"强化学习","slug":"强化学习","count":1,"path":"api/tags/强化学习.json"}],"author":{"name":"这id好怪","slug":"blog-author","avatar":"https://img-blog.csdnimg.cn/20210313122054101.png","link":"/","description":"记录学业、生活、爱好","socials":{"github":"","twitter":"","stackoverflow":"","wechat":"","qq":"","weibo":"","zhihu":"","csdn":"","juejin":"","customs":{}}},"feature":true},{"title":"hexo博客本地预览和github网页不同","uid":"5a13d205332ddf11c6f1ff7dfb511ffd","slug":"hexo博客本地预览和github网页不同","date":"2023-02-21T08:22:48.000Z","updated":"2023-02-21T08:25:11.068Z","comments":true,"path":"api/articles/hexo博客本地预览和github网页不同.json","keywords":null,"cover":null,"text":"一、问题描述修改hexo博客文章标签和分类后，本地预览可以正常显示，上传至github后无法显示 二、解决方案需强制刷新浏览器缓存，Shift+F5刷新，才能显示修改后的新界面 ","link":"","photos":[],"count_time":{"symbolsCount":89,"symbolsTime":"1 mins."},"categories":[{"name":"学习记录","slug":"学习记录","count":2,"path":"api/categories/学习记录.json"}],"tags":[{"name":"小技巧","slug":"小技巧","count":1,"path":"api/tags/小技巧.json"}],"author":{"name":"这id好怪","slug":"blog-author","avatar":"https://img-blog.csdnimg.cn/20210313122054101.png","link":"/","description":"记录学业、生活、爱好","socials":{"github":"","twitter":"","stackoverflow":"","wechat":"","qq":"","weibo":"","zhihu":"","csdn":"","juejin":"","customs":{}}},"feature":true}]}